rxscrite/__init__.py
rxscrite/builtins.py
rxscrite/cli.py
rxscrite/errors.py
rxscrite/interpreter.py
rxscrite/lexer.py
rxscrite/nodes.py
rxscrite/parser.py
rxscrite/symbol_table.py
rxscrite/tokens.py
rxscrite-0.1.0.dist-info/licenses/LICENSE
rxscrite-0.1.0.dist-info/METADATA
rxscrite-0.1.0.dist-info/WHEEL
rxscrite-0.1.0.dist-info/entry_points.txt
rxscrite-0.1.0.dist-info/top_level.txt
rxscrite-0.1.0.dist-info/RECORD
